primordial
